{
    "PathFollowing": {
        "checkpoints": [
            {
                "steps": 8999946,
                "file_path": "results\\Entry_reward01\\PathFollowing\\PathFollowing-8999946.onnx",
                "reward": 8.477142900900011,
                "creation_time": 1655395796.7570512
            },
            {
                "steps": 9499972,
                "file_path": "results\\Entry_reward01\\PathFollowing\\PathFollowing-9499972.onnx",
                "reward": 9.071393622061874,
                "creation_time": 1655404685.8136768
            },
            {
                "steps": 9582734,
                "file_path": "results\\Entry_reward01\\PathFollowing\\PathFollowing-9582734.onnx",
                "reward": 8.388433284958204,
                "creation_time": 1655406191.0741677
            },
            {
                "steps": 9597613,
                "file_path": "results\\Entry_reward01\\PathFollowing\\PathFollowing-9597613.onnx",
                "reward": 9.531516980069378,
                "creation_time": 1655406777.58527
            },
            {
                "steps": 9605292,
                "file_path": "results\\Entry_reward01\\PathFollowing\\PathFollowing-9605292.onnx",
                "reward": 9.38775074109435,
                "creation_time": 1655446628.5475774
            }
        ],
        "final_checkpoint": {
            "steps": 9605292,
            "file_path": "results\\Entry_reward01\\PathFollowing.onnx",
            "reward": 9.38775074109435,
            "creation_time": 1655446628.5475774
        }
    },
    "metadata": {
        "stats_format_version": "0.2.0",
        "mlagents_version": "0.25.0",
        "torch_version": "1.7.1+cu110"
    }
}